LICENSE
delf.py
delf-0.2.1.dist-info/LICENSE
delf-0.2.1.dist-info/METADATA
delf-0.2.1.dist-info/WHEEL
delf-0.2.1.dist-info/entry_points.txt
delf-0.2.1.dist-info/RECORD
