Metadata-Version: 2.1
Name: delf
Version: 0.2.1
Summary: yet another elf dump tool
License: GPL-3.0
Keywords: elf,capstone
Author: terminaldweller
Author-email: devi@terminaldweller.com
Requires-Python: >=3.12,<4.0
Classifier: Environment :: Console
Classifier: License :: OSI Approved :: GNU General Public License v3 (GPLv3)
Classifier: Programming Language :: Python :: 3
Classifier: Programming Language :: Python :: 3.12
Requires-Dist: capstone (>=4.0.2,<5.0.0)
Requires-Dist: setuptools (>=70.0.0,<71.0.0)
